{
  "image_path": "output/non_motor_violations/3号岗厅客流_non_motor_vio_20260508_184042_018.jpg",
  "detection_type": "non_motor_violations",
  "source_type": "single",
  "timestamp": "2026-05-08 18:42:20",
  "vlm_analysis": "{\n    \"signal\": true,\n    \"behavior_type\": \"non_motor_violations\",\n    \"description\": \"红框内是一辆摩托车，车身覆盖有蓝色物品，可见车把和车身结构。\"\n}",
  "parsed_result": {
    "signal": true,
    "behavior_type": "non_motor_violations",
    "description": "红框内是一辆摩托车，车身覆盖有蓝色物品，可见车把和车身结构。"
  }
}