{
  "image_path": "output/non_motor_violations/中电客流3号门进_non_motor_vio_20260510_091106_464.jpg",
  "detection_type": "non_motor_violations",
  "source_type": "single",
  "timestamp": "2026-05-10 09:11:15",
  "vlm_analysis": "{\n    \"signal\": true,\n    \"behavior_type\": \"non_motor_violations\",\n    \"description\": \"红框内清晰显示一辆蓝色的两轮车（摩托车/电动踏板车），可见车把、车身和车轮，符合摩托车特征。\"\n}",
  "parsed_result": {
    "signal": true,
    "behavior_type": "non_motor_violations",
    "description": "红框内清晰显示一辆蓝色的两轮车（摩托车/电动踏板车），可见车把、车身和车轮，符合摩托车特征。"
  }
}