{
  "image_path": "output/non_motor_violations/中电客流3号门进_non_motor_vio_20260511_074534_956.jpg",
  "detection_type": "non_motor_violations",
  "source_type": "single",
  "timestamp": "2026-05-11 07:46:16",
  "vlm_analysis": "{\"signal\": true, \"behavior_type\": \"non_motor_violations\", \"description\": \"红框内清晰可见一辆两轮摩托车（或电动踏板车），具有明显的车身、车轮和车把结构，且有人骑行。\"}",
  "parsed_result": {
    "signal": true,
    "behavior_type": "non_motor_violations",
    "description": "红框内清晰可见一辆两轮摩托车（或电动踏板车），具有明显的车身、车轮和车把结构，且有人骑行。"
  }
}