{
  "image_path": "output/non_motor_violations/洛阳CEC信息港_DigitChan_9_non_motor_vio_20260509_004721_980.jpg",
  "detection_type": "non_motor_violations",
  "source_type": "single",
  "timestamp": "2026-05-09 00:47:43",
  "vlm_analysis": "{\n    \"signal\": false,\n    \"behavior_type\": \"non_motor_violations\",\n    \"description\": \"红框内显示的是白色轿车的左后轮及尾灯部分，属于汽车，非摩托车。\"\n}",
  "parsed_result": {
    "signal": false,
    "behavior_type": "non_motor_violations",
    "description": "红框内显示的是白色轿车的左后轮及尾灯部分，属于汽车，非摩托车。"
  }
}