{
  "image_path": "output/fire_detections/F区2号配电房2_fire_20260508_195606_865.jpg",
  "detection_type": "fire",
  "source_type": "single",
  "timestamp": "2026-05-08 20:16:35",
  "vlm_analysis": "{\n  \"signal\": false,\n  \"behavior_type\": \"false_alarm\",\n  \"description\": \"红色方框内显示的是规则排列的红色光点，结合周围环境（配电房）及地面红色倒影判断，这更像是电气设备的指示灯或光源反光，不具备火焰的不规则跳动特征，属于误报。\"\n}",
  "parsed_result": {
    "signal": false,
    "behavior_type": "false_alarm",
    "description": "红色方框内显示的是规则排列的红色光点，结合周围环境（配电房）及地面红色倒影判断，这更像是电气设备的指示灯或光源反光，不具备火焰的不规则跳动特征，属于误报。"
  }
}