{
  "image_path": "output/fire_detections/中E区2号配电房2_fire_20260509_022552_213.jpg",
  "detection_type": "fire",
  "source_type": "single",
  "timestamp": "2026-05-09 02:26:20",
  "vlm_analysis": "{\n  \"signal\": false,\n  \"behavior_type\": \"false_alarm\",\n  \"description\": \"红色方框内的红色光点排列规则，且与上方及后方电气柜的指示灯特征一致，判断为电气指示灯反光或误报，非真实明火。\"\n}",
  "parsed_result": {
    "signal": false,
    "behavior_type": "false_alarm",
    "description": "红色方框内的红色光点排列规则，且与上方及后方电气柜的指示灯特征一致，判断为电气指示灯反光或误报，非真实明火。"
  }
}