{
  "image_path": "output/fight_detections/A7一楼大厅_fight_20260509_154726_978.jpg",
  "detection_type": "fight",
  "source_type": "single",
  "timestamp": "2026-05-09 15:47:31",
  "vlm_analysis": "{\n  \"signal\": false,\n  \"behavior_type\": \"non_fight\",\n  \"description\": \"画面中仅有一名人员独自站立或行走，周围无其他人员与其发生肢体接触或互动，未观察到挥拳、踢腿、推搡等暴力行为迹象。\"\n}",
  "parsed_result": {
    "signal": false,
    "behavior_type": "non_fight",
    "description": "画面中仅有一名人员独自站立或行走，周围无其他人员与其发生肢体接触或互动，未观察到挥拳、踢腿、推搡等暴力行为迹象。"
  }
}