{
  "image_path": "output/motor_vehicle_violations/南门客流右_motor_vio_20260509_231629_428.jpg",
  "detection_type": "motor_vehicle_violations",
  "source_type": "single",
  "timestamp": "2026-05-09 23:16:43",
  "vlm_analysis": "{\n    \"signal\": true,\n    \"behavior_type\": \"motor_vehicle_violations\",\n    \"description\": \"红框内清晰可见一辆白色轿车，具有明显的车头、大灯和车窗结构，主体占据红框主要区域，确认为机动车目标。\"\n}",
  "parsed_result": {
    "signal": true,
    "behavior_type": "motor_vehicle_violations",
    "description": "红框内清晰可见一辆白色轿车，具有明显的车头、大灯和车窗结构，主体占据红框主要区域，确认为机动车目标。"
  }
}